stack/__init__.py
stack/stack.py
dsstack8-0.0.1.dist-info/LICENSE
dsstack8-0.0.1.dist-info/METADATA
dsstack8-0.0.1.dist-info/WHEEL
dsstack8-0.0.1.dist-info/top_level.txt
dsstack8-0.0.1.dist-info/RECORD
